historydict.py
historydict-1.2.6.dist-info/LICENSE
historydict-1.2.6.dist-info/METADATA
historydict-1.2.6.dist-info/WHEEL
historydict-1.2.6.dist-info/top_level.txt
historydict-1.2.6.dist-info/RECORD
